wgtray
