Metadata-Version: 2.1
Name: wg-tray
Version: 0.1.1
Summary: A simple graphical tool to manage wireguard interfaces from the system tray
Home-page: https://wg-tray.arcanite.ch/
Author: Elsa Weber
Author-email: elsa.weber@arcanite.ch
License: LICENSE.txt
Platform: UNKNOWN
License-File: LICENSE.txt
